perigene/__init__.py
perigene/cli.py
perigene/commands/__init__.py
perigene/commands/callbacks.py
perigene/commands/cmd_preprocessing.py
perigene/commands/cmd_run.py
perigene/commands/cmd_step.py
perigene/commands/params_shared.py
perigene/commands/params_utils.py
perigene/commands/subcmds_preprocessing/__init__.py
perigene/commands/subcmds_preprocessing/subcmd_magma.py
perigene/commands/subcmds_preprocessing/subcmd_merge_features.py
perigene/commands/subcmds_step/__init__.py
perigene/commands/subcmds_step/subcmd_feature_selection.py
perigene/commands/subcmds_step/subcmd_predict.py
perigene/commands/subcmds_step/subcmd_tuning.py
perigene/constants.py
perigene/data.py
perigene/data_tables.py
perigene/exceptions.py
perigene/feature_selection.py
perigene/index.py
perigene/info.py
perigene/models.py
perigene/perigene_types.py
perigene/preprocessing/__init__.py
perigene/preprocessing/features_files.py
perigene/preprocessing/features_merging.py
perigene/preprocessing/magma_output.py
perigene/training.py
perigene/tuning.py
perigene/utils.py
perigene-0.3.1.dist-info/LICENSE
perigene-0.3.1.dist-info/METADATA
perigene-0.3.1.dist-info/WHEEL
perigene-0.3.1.dist-info/entry_points.txt
perigene-0.3.1.dist-info/RECORD
