Metadata-Version: 2.1
Name: perigene
Version: 0.3.1
Summary: Polygenenic Enrichment for Risk Gene prioritization: a CLI tool and package to prioritize risk genes from GWAS summary statistics and gene features
License: MIT
Author: Theo Dupuis
Author-email: me@theodupuis.io
Requires-Python: >=3.10,<4.0
Classifier: License :: OSI Approved :: MIT License
Classifier: Programming Language :: Python :: 3
Classifier: Programming Language :: Python :: 3.10
Classifier: Programming Language :: Python :: 3.11
Classifier: Programming Language :: Python :: 3.12
Requires-Dist: click (>=8.1.3,<9.0.0)
Requires-Dist: click-option-group (>=0.5.5,<0.6.0)
Requires-Dist: fastparquet (>=2022.12.0,<2023.0.0)
Requires-Dist: filelock (>=3.13.1,<4.0.0)
Requires-Dist: natsort (>=8.2.0,<9.0.0)
Requires-Dist: numpy (>=1.23.4,<2.0.0)
Requires-Dist: optuna (>=3.1.0,<4.0.0)
Requires-Dist: pandas (>=1.5.1,<2.0.0)
Requires-Dist: pyarrow (>=14.0.2,<15.0.0)
Requires-Dist: scikit-learn (>=1.1.3,<2.0.0)
Requires-Dist: statsmodels (>=0.13.5,<0.14.0)
Requires-Dist: xgboost (>=2,<3)
